cdnmon/__init__.py
cdnmon/model/cdn/__init__.py
cdnmon/model/cdn/adobe.py
cdnmon/model/cdn/advancedhosting.py
cdnmon/model/cdn/akamai.py
cdnmon/model/cdn/alibaba_cdn.py
cdnmon/model/cdn/alibaba_dcdn.py
cdnmon/model/cdn/alibaba_waf.py
cdnmon/model/cdn/asia_isp.py
cdnmon/model/cdn/azion.py
cdnmon/model/cdn/baidu.py
cdnmon/model/cdn/baishan.py
cdnmon/model/cdn/beluga.py
cdnmon/model/cdn/blazingcdn.py
cdnmon/model/cdn/bunny.py
cdnmon/model/cdn/byteplus.py
cdnmon/model/cdn/cachefly.py
cdnmon/model/cdn/cdn77.py
cdnmon/model/cdn/cdnetworks.py
cdnmon/model/cdn/cdnsun.py
cdnmon/model/cdn/cdnvideo.py
cdnmon/model/cdn/chinacache.py
cdnmon/model/cdn/chinanet.py
cdnmon/model/cdn/cloudflare.py
cdnmon/model/cdn/cloudfront.py
cdnmon/model/cdn/ctyun.py
cdnmon/model/cdn/dnion.py
cdnmon/model/cdn/douyin.py
cdnmon/model/cdn/edgecast.py
cdnmon/model/cdn/edgio.py
cdnmon/model/cdn/facebook.py
cdnmon/model/cdn/fastly.py
cdnmon/model/cdn/fastly_edge_compute.py
cdnmon/model/cdn/frontdoor.py
cdnmon/model/cdn/gcore.py
cdnmon/model/cdn/huawei.py
cdnmon/model/cdn/hubspot.py
cdnmon/model/cdn/imperva.py
cdnmon/model/cdn/incapsula.py
cdnmon/model/cdn/inxy.py
cdnmon/model/cdn/iverycloud.py
cdnmon/model/cdn/jingdong.py
cdnmon/model/cdn/keycdn.py
cdnmon/model/cdn/kingsoft.py
cdnmon/model/cdn/leaseweb.py
cdnmon/model/cdn/limelight.py
cdnmon/model/cdn/lumen.py
cdnmon/model/cdn/netlify.py
cdnmon/model/cdn/ngenix.py
cdnmon/model/cdn/qihoo.py
cdnmon/model/cdn/qiniu.py
cdnmon/model/cdn/reblaze.py
cdnmon/model/cdn/salesforce.py
cdnmon/model/cdn/sitelock.py
cdnmon/model/cdn/tencent.py
cdnmon/model/cdn/todo/afx.py
cdnmon/model/cdn/todo/agile.py
cdnmon/model/cdn/todo/ananke.py
cdnmon/model/cdn/todo/aodianyun.py
cdnmon/model/cdn/todo/arvancloud.py
cdnmon/model/cdn/todo/att.py
cdnmon/model/cdn/todo/cdnify.py
cdnmon/model/cdn/todo/cedexis.py
cdnmon/model/cdn/todo/cotendo.py
cdnmon/model/cdn/todo/cube.py
cdnmon/model/cdn/todo/ddos-guard.py
cdnmon/model/cdn/todo/digitalink.py
cdnmon/model/cdn/todo/edgenext.py
cdnmon-0.5.14.dist-info/METADATA
cdnmon-0.5.14.dist-info/WHEEL
cdnmon-0.5.14.dist-info/RECORD
